[
  {
    "id": "0e641453-c489-41aa-8480-b0976d16c74a",
    "runId": "2fa166eb-a999-496e-bd28-b20efd0b5c8f",
    "implId": "graphql-go",
    "testCaseId": "03573f34/2e32a08b/08277c86",
    "status": "fail",
    "expected": {
      "data": {
        "__typename": "Object_lpJFn",
        "H3Nl_": "Object_lpJFn",
        "puaq39dlg": {
          "deWZL": "XtCw_c"
        }
      }
    },
    "actual": {
      "data": null,
      "errors": [
        {
          "message": "Syntax Error GraphQL request (1:33) Expected $, found @\n\n1: query ($kJ8hrxR: Boolean! = true@Directive_RtXxkf) {\n                                   ^\n2:   ...Fragment_Q\n",
          "locations": [
            {
              "line": 1,
              "column": 33
            }
          ]
        }
      ]
    }
  },
  {
    "id": "71fbbd74-0302-4e82-83e6-79e098e1dd61",
    "runId": "2fa166eb-a999-496e-bd28-b20efd0b5c8f",
    "implId": "graphql-go",
    "testCaseId": "03573f34/2e32a08b/179ab86c",
    "status": "fail",
    "expected": {
      "data": {
        "__typename": "Object_lpJFn",
        "H3Nl_": "Object_lpJFn",
        "puaq39dlg": {
          "deWZL": "XtCw_c"
        }
      }
    },
    "actual": {
      "data": null,
      "errors": [
        {
          "message": "Syntax Error GraphQL request (1:33) Expected $, found @\n\n1: query ($kJ8hrxR: Boolean! = true@Directive_RtXxkf) {\n                                   ^\n2:   ...Fragment_Q\n",
          "locations": [
            {
              "line": 1,
              "column": 33
            }
          ]
        }
      ]
    }
  },
  {
    "id": "71d2b54a-884a-4566-870d-3ead530ed6b8",
    "runId": "2fa166eb-a999-496e-bd28-b20efd0b5c8f",
    "implId": "graphql-go",
    "testCaseId": "03573f34/844439df/3cbd2fee",
    "status": "fail",
    "expected": {
      "data": {
        "__typename": "Object_lpJFn"
      }
    },
    "actual": {
      "data": null,
      "errors": [
        {
          "message": "Syntax Error GraphQL request (1:36) Expected $, found @\n\n1: query y90y6ZiH9($u4jGeH6z: Boolean!@Directive_RtXxkf) {\n                                      ^\n2:   ... on Object_lpJFn {\n",
          "locations": [
            {
              "line": 1,
              "column": 36
            }
          ]
        }
      ]
    }
  },
  {
    "id": "1a97c4ce-eefe-42a0-860d-7472721f5298",
    "runId": "2fa166eb-a999-496e-bd28-b20efd0b5c8f",
    "implId": "graphql-go",
    "testCaseId": "03573f34/844439df/64d17f61",
    "status": "fail",
    "expected": {
      "data": {
        "__typename": "Object_lpJFn"
      }
    },
    "actual": {
      "data": null,
      "errors": [
        {
          "message": "Syntax Error GraphQL request (1:36) Expected $, found @\n\n1: query y90y6ZiH9($u4jGeH6z: Boolean!@Directive_RtXxkf) {\n                                      ^\n2:   ... on Object_lpJFn {\n",
          "locations": [
            {
              "line": 1,
              "column": 36
            }
          ]
        }
      ]
    }
  },
  {
    "id": "1a18307f-4518-44a4-8ddc-2809dc6f2ab3",
    "runId": "2fa166eb-a999-496e-bd28-b20efd0b5c8f",
    "implId": "graphql-go",
    "testCaseId": "03573f34/db6ebcb1/457e9b63",
    "status": "fail",
    "expected": {
      "data": {
        "P": "Object_lpJFn",
        "oM": "Object_lpJFn"
      }
    },
    "actual": {
      "data": null,
      "errors": [
        {
          "message": "Variable \"$rbEuY2\" of type \"Boolean!\" is required and will not use the default value. Perhaps you meant to use type \"Boolean\".",
          "locations": [
            {
              "line": 1,
              "column": 36
            }
          ]
        }
      ]
    }
  },
  {
    "id": "0b81f9d2-8418-4aa8-88e2-557decf42629",
    "runId": "2fa166eb-a999-496e-bd28-b20efd0b5c8f",
    "implId": "graphql-go",
    "testCaseId": "03573f34/db6ebcb1/b116a709",
    "status": "fail",
    "expected": {
      "data": {
        "P": "Object_lpJFn"
      }
    },
    "actual": {
      "data": null,
      "errors": [
        {
          "message": "Variable \"$rbEuY2\" of type \"Boolean!\" is required and will not use the default value. Perhaps you meant to use type \"Boolean\".",
          "locations": [
            {
              "line": 1,
              "column": 36
            }
          ]
        }
      ]
    }
  },
  {
    "id": "70d02462-1059-4617-8f6f-29fd25424d3d",
    "runId": "2fa166eb-a999-496e-bd28-b20efd0b5c8f",
    "implId": "graphql-go",
    "testCaseId": "0565cafd/e841846b/44136fa3",
    "status": "fail",
    "expected": {
      "data": {
        "__typename": "Object_bd",
        "j": [
          {
            "__typename": "Interface_U61e_STUB"
          },
          {
            "__typename": "Interface_U61e_STUB"
          }
        ],
        "jrWn": true,
        "ikBVofJQ": true
      }
    },
    "actual": {
      "data": null,
      "errors": [
        {
          "message": "Syntax Error GraphQL request (8:14) Unexpected Name \"null\"\n\n7:   ... on Object_bd {\n8:     jrWn(au: null)\n                ^\n9:   }\n",
          "locations": [
            {
              "line": 8,
              "column": 14
            }
          ]
        }
      ]
    }
  },
  {
    "id": "66b1859d-b464-4e0b-86fe-b8028e62d947",
    "runId": "2fa166eb-a999-496e-bd28-b20efd0b5c8f",
    "implId": "graphql-go",
    "testCaseId": "0565cafd/e841846b/6dfb7769",
    "status": "fail",
    "expected": {
      "data": {
        "__typename": "Object_bd",
        "j": [
          {
            "__typename": "Interface_U61e_STUB"
          },
          {
            "__typename": "Interface_U61e_STUB"
          }
        ],
        "jrWn": true,
        "ikBVofJQ": true
      }
    },
    "actual": {
      "data": null,
      "errors": [
        {
          "message": "Syntax Error GraphQL request (8:14) Unexpected Name \"null\"\n\n7:   ... on Object_bd {\n8:     jrWn(au: null)\n                ^\n9:   }\n",
          "locations": [
            {
              "line": 8,
              "column": 14
            }
          ]
        }
      ]
    }
  },
  {
    "id": "c9ca7ca9-fb5a-44a6-8705-b376a9f6b236",
    "runId": "2fa166eb-a999-496e-bd28-b20efd0b5c8f",
    "implId": "graphql-go",
    "testCaseId": "0565cafd/e841846b/852980e1",
    "status": "fail",
    "expected": {
      "data": {
        "__typename": "Object_bd",
        "j": [
          {
            "__typename": "Interface_U61e_STUB"
          },
          {
            "__typename": "Interface_U61e_STUB"
          }
        ],
        "jrWn": true,
        "ikBVofJQ": true
      }
    },
    "actual": {
      "data": null,
      "errors": [
        {
          "message": "Syntax Error GraphQL request (8:14) Unexpected Name \"null\"\n\n7:   ... on Object_bd {\n8:     jrWn(au: null)\n                ^\n9:   }\n",
          "locations": [
            {
              "line": 8,
              "column": 14
            }
          ]
        }
      ]
    }
  },
  {
    "id": "b7246a34-c4d7-416a-8d7c-7b7e5eec35b1",
    "runId": "2fa166eb-a999-496e-bd28-b20efd0b5c8f",
    "implId": "graphql-go",
    "testCaseId": "0565cafd/eac9c424/44136fa3",
    "status": "fail",
    "expected": {
      "data": {
        "UnXJTyzQ": [
          {
            "wjZ8": "Interface_U61e_STUB",
            "__typename": "Interface_U61e_STUB",
            "gi6VAY": [
              true,
              true
            ]
          },
          {
            "wjZ8": "Interface_U61e_STUB",
            "__typename": "Interface_U61e_STUB",
            "gi6VAY": [
              true,
              true
            ]
          }
        ],
        "jrWn": true,
        "__typename": "Object_bd"
      }
    },
    "actual": {
      "data": null,
      "errors": [
        {
          "message": "Fragment cannot be spread here as objects of type \"Interface_U61e\" can never be of type \"[Interface_U61e]!\".",
          "locations": [
            {
              "line": 3,
              "column": 5
            }
          ]
        }
      ]
    }
  }
]
