[
  {
    "id": "be67d363-00b5-4656-826e-e44d71eb83f3",
    "runId": "ff8f7f30-2fbf-4906-9630-d581af34bef7",
    "implId": "absinthe",
    "testCaseId": "03573f34/2e32a08b/08277c86",
    "status": "error",
    "expected": {
      "data": {
        "__typename": "Object_lpJFn",
        "H3Nl_": "Object_lpJFn",
        "puaq39dlg": {
          "deWZL": "XtCw_c"
        }
      }
    },
    "error": "no function clause matching in Absinthe.Blueprint.Directive.placement/1",
    "stderr": "{\"errors\":[{\"message\":\"no function clause matching in Absinthe.Blueprint.Directive.placement/1\"}]}"
  },
  {
    "id": "89a59319-af3a-4c68-85e3-c8aa12cb5526",
    "runId": "ff8f7f30-2fbf-4906-9630-d581af34bef7",
    "implId": "absinthe",
    "testCaseId": "03573f34/2e32a08b/179ab86c",
    "status": "error",
    "expected": {
      "data": {
        "__typename": "Object_lpJFn",
        "H3Nl_": "Object_lpJFn",
        "puaq39dlg": {
          "deWZL": "XtCw_c"
        }
      }
    },
    "error": "no function clause matching in Absinthe.Blueprint.Directive.placement/1",
    "stderr": "{\"errors\":[{\"message\":\"no function clause matching in Absinthe.Blueprint.Directive.placement/1\"}]}"
  },
  {
    "id": "8c1295c8-63d8-4411-8eba-178555660dd1",
    "runId": "ff8f7f30-2fbf-4906-9630-d581af34bef7",
    "implId": "absinthe",
    "testCaseId": "067e429f/104a4553/44136fa3",
    "status": "error",
    "expected": {
      "data": {
        "__typename": "Object_U92jm3n0Y"
      }
    },
    "error": "Compilation failed:\n---------------------------------------\n## Locations\nnofile:0\n\nField name \"__yyo2pb\" starts with two leading underscores.\n\nType system artifacts must not begin with two leading underscores.\n\n> GraphQL type system authors must not define any types, fields, arguments,\n> or any other type system artifact with two leading underscores.\n\nReference: https://github.com/facebook/graphql/blob/master/spec/Section%204%20--%20Introspection.md#naming-conventions\n\n",
    "stderr": "{\"errors\":[{\"message\":\"Compilation failed:\\n---------------------------------------\\n## Locations\\nnofile:0\\n\\nField name \\\"__yyo2pb\\\" starts with two leading underscores.\\n\\nType system artifacts must not begin with two leading underscores.\\n\\n> GraphQL type system authors must not define any types, fields, arguments,\\n> or any other type system artifact with two leading underscores.\\n\\nReference: https://github.com/facebook/graphql/blob/master/spec/Section%204%20--%20Introspection.md#naming-conventions\\n\\n\"}]}"
  },
  {
    "id": "e7f7178e-cd23-4bea-8fde-c06a35cfa7ff",
    "runId": "ff8f7f30-2fbf-4906-9630-d581af34bef7",
    "implId": "absinthe",
    "testCaseId": "067e429f/2edf4c47/40f37770",
    "status": "error",
    "expected": {
      "data": {
        "pWI9NE8VQ": {
          "cgu": "str"
        },
        "cgu": "str",
        "__typename": "Object_U92jm3n0Y"
      }
    },
    "error": "Compilation failed:\n---------------------------------------\n## Locations\nnofile:0\n\nField name \"__yyo2pb\" starts with two leading underscores.\n\nType system artifacts must not begin with two leading underscores.\n\n> GraphQL type system authors must not define any types, fields, arguments,\n> or any other type system artifact with two leading underscores.\n\nReference: https://github.com/facebook/graphql/blob/master/spec/Section%204%20--%20Introspection.md#naming-conventions\n\n",
    "stderr": "{\"errors\":[{\"message\":\"Compilation failed:\\n---------------------------------------\\n## Locations\\nnofile:0\\n\\nField name \\\"__yyo2pb\\\" starts with two leading underscores.\\n\\nType system artifacts must not begin with two leading underscores.\\n\\n> GraphQL type system authors must not define any types, fields, arguments,\\n> or any other type system artifact with two leading underscores.\\n\\nReference: https://github.com/facebook/graphql/blob/master/spec/Section%204%20--%20Introspection.md#naming-conventions\\n\\n\"}]}"
  },
  {
    "id": "96ce5b62-049e-45aa-8c32-5d1d9d316180",
    "runId": "ff8f7f30-2fbf-4906-9630-d581af34bef7",
    "implId": "absinthe",
    "testCaseId": "067e429f/2edf4c47/f444c2b7",
    "status": "error",
    "expected": {
      "data": {
        "pWI9NE8VQ": {},
        "cgu": "str",
        "__typename": "Object_U92jm3n0Y"
      }
    },
    "error": "Compilation failed:\n---------------------------------------\n## Locations\nnofile:0\n\nField name \"__yyo2pb\" starts with two leading underscores.\n\nType system artifacts must not begin with two leading underscores.\n\n> GraphQL type system authors must not define any types, fields, arguments,\n> or any other type system artifact with two leading underscores.\n\nReference: https://github.com/facebook/graphql/blob/master/spec/Section%204%20--%20Introspection.md#naming-conventions\n\n",
    "stderr": "{\"errors\":[{\"message\":\"Compilation failed:\\n---------------------------------------\\n## Locations\\nnofile:0\\n\\nField name \\\"__yyo2pb\\\" starts with two leading underscores.\\n\\nType system artifacts must not begin with two leading underscores.\\n\\n> GraphQL type system authors must not define any types, fields, arguments,\\n> or any other type system artifact with two leading underscores.\\n\\nReference: https://github.com/facebook/graphql/blob/master/spec/Section%204%20--%20Introspection.md#naming-conventions\\n\\n\"}]}"
  },
  {
    "id": "f2eb7cc1-f2d6-40e9-8b16-c6ef4d3a2f5d",
    "runId": "ff8f7f30-2fbf-4906-9630-d581af34bef7",
    "implId": "absinthe",
    "testCaseId": "067e429f/32346071/44136fa3",
    "status": "error",
    "expected": {
      "data": {}
    },
    "error": "Compilation failed:\n---------------------------------------\n## Locations\nnofile:0\n\nField name \"__yyo2pb\" starts with two leading underscores.\n\nType system artifacts must not begin with two leading underscores.\n\n> GraphQL type system authors must not define any types, fields, arguments,\n> or any other type system artifact with two leading underscores.\n\nReference: https://github.com/facebook/graphql/blob/master/spec/Section%204%20--%20Introspection.md#naming-conventions\n\n",
    "stderr": "{\"errors\":[{\"message\":\"Compilation failed:\\n---------------------------------------\\n## Locations\\nnofile:0\\n\\nField name \\\"__yyo2pb\\\" starts with two leading underscores.\\n\\nType system artifacts must not begin with two leading underscores.\\n\\n> GraphQL type system authors must not define any types, fields, arguments,\\n> or any other type system artifact with two leading underscores.\\n\\nReference: https://github.com/facebook/graphql/blob/master/spec/Section%204%20--%20Introspection.md#naming-conventions\\n\\n\"}]}"
  },
  {
    "id": "914790db-4cb0-4863-8bdc-258d104e4d95",
    "runId": "ff8f7f30-2fbf-4906-9630-d581af34bef7",
    "implId": "absinthe",
    "testCaseId": "067e429f/53dcaa6b/44136fa3",
    "status": "error",
    "expected": {
      "data": {
        "__typename": "Object_U92jm3n0Y",
        "pWI9NE8VQ": {
          "__typename": "Object_U92jm3n0Y"
        }
      }
    },
    "error": "Compilation failed:\n---------------------------------------\n## Locations\nnofile:0\n\nField name \"__yyo2pb\" starts with two leading underscores.\n\nType system artifacts must not begin with two leading underscores.\n\n> GraphQL type system authors must not define any types, fields, arguments,\n> or any other type system artifact with two leading underscores.\n\nReference: https://github.com/facebook/graphql/blob/master/spec/Section%204%20--%20Introspection.md#naming-conventions\n\n",
    "stderr": "{\"errors\":[{\"message\":\"Compilation failed:\\n---------------------------------------\\n## Locations\\nnofile:0\\n\\nField name \\\"__yyo2pb\\\" starts with two leading underscores.\\n\\nType system artifacts must not begin with two leading underscores.\\n\\n> GraphQL type system authors must not define any types, fields, arguments,\\n> or any other type system artifact with two leading underscores.\\n\\nReference: https://github.com/facebook/graphql/blob/master/spec/Section%204%20--%20Introspection.md#naming-conventions\\n\\n\"}]}"
  },
  {
    "id": "e815b210-a1ea-4bd9-832e-1f0263c72238",
    "runId": "ff8f7f30-2fbf-4906-9630-d581af34bef7",
    "implId": "absinthe",
    "testCaseId": "067e429f/5989b27f/211a8742",
    "status": "error",
    "expected": {
      "data": {
        "cgu": "str",
        "YQJ1O9": {
          "E": {
            "XT00gnpI": "Object_U92jm3n0Y"
          },
          "cgu": "str",
          "gVMW": "Object_U92jm3n0Y"
        }
      }
    },
    "error": "Compilation failed:\n---------------------------------------\n## Locations\nnofile:0\n\nField name \"__yyo2pb\" starts with two leading underscores.\n\nType system artifacts must not begin with two leading underscores.\n\n> GraphQL type system authors must not define any types, fields, arguments,\n> or any other type system artifact with two leading underscores.\n\nReference: https://github.com/facebook/graphql/blob/master/spec/Section%204%20--%20Introspection.md#naming-conventions\n\n",
    "stderr": "{\"errors\":[{\"message\":\"Compilation failed:\\n---------------------------------------\\n## Locations\\nnofile:0\\n\\nField name \\\"__yyo2pb\\\" starts with two leading underscores.\\n\\nType system artifacts must not begin with two leading underscores.\\n\\n> GraphQL type system authors must not define any types, fields, arguments,\\n> or any other type system artifact with two leading underscores.\\n\\nReference: https://github.com/facebook/graphql/blob/master/spec/Section%204%20--%20Introspection.md#naming-conventions\\n\\n\"}]}"
  },
  {
    "id": "d276757a-f857-4627-835c-116339993cbc",
    "runId": "ff8f7f30-2fbf-4906-9630-d581af34bef7",
    "implId": "absinthe",
    "testCaseId": "067e429f/5989b27f/2eb49031",
    "status": "error",
    "expected": {
      "data": {
        "cgu": "str",
        "YQJ1O9": {
          "E": {
            "XT00gnpI": "Object_U92jm3n0Y"
          },
          "cgu": "str",
          "gVMW": "Object_U92jm3n0Y"
        }
      }
    },
    "error": "Compilation failed:\n---------------------------------------\n## Locations\nnofile:0\n\nField name \"__yyo2pb\" starts with two leading underscores.\n\nType system artifacts must not begin with two leading underscores.\n\n> GraphQL type system authors must not define any types, fields, arguments,\n> or any other type system artifact with two leading underscores.\n\nReference: https://github.com/facebook/graphql/blob/master/spec/Section%204%20--%20Introspection.md#naming-conventions\n\n",
    "stderr": "{\"errors\":[{\"message\":\"Compilation failed:\\n---------------------------------------\\n## Locations\\nnofile:0\\n\\nField name \\\"__yyo2pb\\\" starts with two leading underscores.\\n\\nType system artifacts must not begin with two leading underscores.\\n\\n> GraphQL type system authors must not define any types, fields, arguments,\\n> or any other type system artifact with two leading underscores.\\n\\nReference: https://github.com/facebook/graphql/blob/master/spec/Section%204%20--%20Introspection.md#naming-conventions\\n\\n\"}]}"
  },
  {
    "id": "256b67a4-e0cd-4769-81bd-d01557b2a69f",
    "runId": "ff8f7f30-2fbf-4906-9630-d581af34bef7",
    "implId": "absinthe",
    "testCaseId": "067e429f/5989b27f/b0443fa6",
    "status": "error",
    "expected": {
      "data": {
        "cgu": "str",
        "YQJ1O9": {
          "E": {
            "XT00gnpI": "Object_U92jm3n0Y"
          },
          "cgu": "str",
          "gVMW": "Object_U92jm3n0Y"
        }
      }
    },
    "error": "Compilation failed:\n---------------------------------------\n## Locations\nnofile:0\n\nField name \"__yyo2pb\" starts with two leading underscores.\n\nType system artifacts must not begin with two leading underscores.\n\n> GraphQL type system authors must not define any types, fields, arguments,\n> or any other type system artifact with two leading underscores.\n\nReference: https://github.com/facebook/graphql/blob/master/spec/Section%204%20--%20Introspection.md#naming-conventions\n\n",
    "stderr": "{\"errors\":[{\"message\":\"Compilation failed:\\n---------------------------------------\\n## Locations\\nnofile:0\\n\\nField name \\\"__yyo2pb\\\" starts with two leading underscores.\\n\\nType system artifacts must not begin with two leading underscores.\\n\\n> GraphQL type system authors must not define any types, fields, arguments,\\n> or any other type system artifact with two leading underscores.\\n\\nReference: https://github.com/facebook/graphql/blob/master/spec/Section%204%20--%20Introspection.md#naming-conventions\\n\\n\"}]}"
  }
]
