[
  {
    "id": "a5ba6cd3-8d76-4cbe-86c7-5450a290c33b",
    "runId": "98066558-0116-4a89-b5e3-aac20bd1298f",
    "implId": "async-graphql",
    "testCaseId": "034907e7/08233559/724a47a1",
    "status": "fail",
    "expected": {
      "data": {
        "__typename": "Object_jGekrLP4U",
        "c5GCEDZ": "id",
        "n_kMSMjl": "id"
      }
    },
    "actual": {
      "data": {
        "__typename": "Object_jGekrLP4U",
        "n_kMSMjl": "id"
      }
    }
  },
  {
    "id": "1cd3d906-98f5-4fe3-82e5-67b4e55e6048",
    "runId": "98066558-0116-4a89-b5e3-aac20bd1298f",
    "implId": "async-graphql",
    "testCaseId": "034907e7/09274984/e1d651ba",
    "status": "fail",
    "expected": {
      "data": {
        "Uf": "Object_jGekrLP4U",
        "__typename": "Object_jGekrLP4U",
        "a": "id"
      }
    },
    "actual": {
      "data": null
    }
  },
  {
    "id": "0b914f87-4b53-4d80-806b-776d36962434",
    "runId": "98066558-0116-4a89-b5e3-aac20bd1298f",
    "implId": "async-graphql",
    "testCaseId": "034907e7/09274984/f00482f3",
    "status": "fail",
    "expected": {
      "data": {
        "Uf": "Object_jGekrLP4U",
        "__typename": "Object_jGekrLP4U",
        "a": "id"
      }
    },
    "actual": {
      "data": null
    }
  },
  {
    "id": "b3749189-a6f9-4599-8781-c97ce19e307e",
    "runId": "98066558-0116-4a89-b5e3-aac20bd1298f",
    "implId": "async-graphql",
    "testCaseId": "034907e7/5f421a36/44136fa3",
    "status": "fail",
    "expected": {
      "data": {
        "lPfrwoN": "Object_jGekrLP4U"
      }
    },
    "actual": {
      "data": null
    }
  },
  {
    "id": "9aacf902-fc83-4ec9-84b8-06f43fc2246a",
    "runId": "98066558-0116-4a89-b5e3-aac20bd1298f",
    "implId": "async-graphql",
    "testCaseId": "034907e7/7990cc4f/44136fa3",
    "status": "fail",
    "expected": {
      "data": {
        "dQ6WtE34": true,
        "__typename": "Object_jGekrLP4U"
      }
    },
    "actual": {
      "data": {
        "dQ6WtE34": true
      }
    }
  },
  {
    "id": "f14f222e-f987-40d2-829b-a8862cbe6cdc",
    "runId": "98066558-0116-4a89-b5e3-aac20bd1298f",
    "implId": "async-graphql",
    "testCaseId": "034907e7/93c616f0/44136fa3",
    "status": "fail",
    "expected": {
      "data": {
        "__typename": "Object_jGekrLP4U",
        "c5GCEDZ": "id"
      }
    },
    "actual": {
      "data": {
        "c5GCEDZ": "id"
      }
    }
  },
  {
    "id": "c5b73fb7-3f4e-427f-8650-a49c7b12f367",
    "runId": "98066558-0116-4a89-b5e3-aac20bd1298f",
    "implId": "async-graphql",
    "testCaseId": "034907e7/ea93ad2f/44136fa3",
    "status": "fail",
    "expected": {
      "data": {
        "__typename": "Object_jGekrLP4U",
        "L": "Object_jGekrLP4U",
        "a": "id"
      }
    },
    "actual": {
      "data": {
        "a": "id"
      }
    }
  },
  {
    "id": "fa9d2857-86ca-4cdc-81b7-89f1f2452676",
    "runId": "98066558-0116-4a89-b5e3-aac20bd1298f",
    "implId": "async-graphql",
    "testCaseId": "034907e7/f08f01a6/44136fa3",
    "status": "fail",
    "expected": {
      "data": {
        "y9Sef": "Object_jGekrLP4U",
        "__typename": "Object_jGekrLP4U"
      }
    },
    "actual": {
      "data": null
    }
  },
  {
    "id": "ed05bdd4-e42b-441c-8b55-0400f435e7fd",
    "runId": "98066558-0116-4a89-b5e3-aac20bd1298f",
    "implId": "async-graphql",
    "testCaseId": "03573f34/0bddac9f/44136fa3",
    "status": "fail",
    "expected": {
      "data": {
        "__typename": "Object_lpJFn"
      }
    },
    "actual": {
      "data": null
    }
  },
  {
    "id": "30376747-6417-4121-8ed3-4579ce977b25",
    "runId": "98066558-0116-4a89-b5e3-aac20bd1298f",
    "implId": "async-graphql",
    "testCaseId": "03573f34/1a4227c3/44136fa3",
    "status": "fail",
    "expected": {
      "data": {
        "__typename": "Object_lpJFn",
        "xunqtFHE": "Object_lpJFn",
        "x4cbu6cZ": {
          "__typename": "Interface_j4AUR_STUB",
          "R5Ldbv_": {
            "gf": true
          },
          "wvF": "Interface_j4AUR_STUB",
          "deWZL": "XtCw_c",
          "zhKE": {
            "ITX": "Interface_D_STUB"
          }
        },
        "msiDCGEKr": "Object_lpJFn"
      }
    },
    "actual": {
      "data": {
        "__typename": "Object_lpJFn",
        "x4cbu6cZ": {
          "R5Ldbv_": {
            "gf": true
          },
          "__typename": "Interface_j4AUR_STUB",
          "deWZL": "XtCw_c",
          "wvF": "Interface_j4AUR_STUB",
          "zhKE": {
            "ITX": "Interface_D_STUB"
          }
        },
        "xunqtFHE": "Object_lpJFn"
      }
    }
  }
]
