[
  {
    "id": "f856a6ee-f724-4154-80c8-05df5a509bf2",
    "runId": "7e79c07d-6ca7-4846-894c-ccddf4dfb6c6",
    "implId": "absinthe",
    "testCaseId": "03573f34/2e32a08b/08277c86",
    "status": "error",
    "expected": {
      "data": {
        "__typename": "Object_lpJFn",
        "H3Nl_": "Object_lpJFn",
        "puaq39dlg": {
          "deWZL": "XtCw_c"
        }
      }
    },
    "error": "no function clause matching in Absinthe.Blueprint.Directive.placement/1",
    "stderr": "{\"errors\":[{\"message\":\"no function clause matching in Absinthe.Blueprint.Directive.placement/1\"}]}"
  },
  {
    "id": "099aa67b-b85a-4696-8420-573ded086a1c",
    "runId": "7e79c07d-6ca7-4846-894c-ccddf4dfb6c6",
    "implId": "absinthe",
    "testCaseId": "03573f34/2e32a08b/179ab86c",
    "status": "error",
    "expected": {
      "data": {
        "__typename": "Object_lpJFn",
        "H3Nl_": "Object_lpJFn",
        "puaq39dlg": {
          "deWZL": "XtCw_c"
        }
      }
    },
    "error": "no function clause matching in Absinthe.Blueprint.Directive.placement/1",
    "stderr": "{\"errors\":[{\"message\":\"no function clause matching in Absinthe.Blueprint.Directive.placement/1\"}]}"
  },
  {
    "id": "e7dbd748-28e7-4a2a-8934-f3dc51dbd35e",
    "runId": "7e79c07d-6ca7-4846-894c-ccddf4dfb6c6",
    "implId": "absinthe",
    "testCaseId": "067e429f/104a4553/44136fa3",
    "status": "error",
    "expected": {
      "data": {
        "__typename": "Object_U92jm3n0Y"
      }
    },
    "error": "Compilation failed:\n---------------------------------------\n## Locations\nnofile:0\n\nField name \"__yyo2pb\" starts with two leading underscores.\n\nType system artifacts must not begin with two leading underscores.\n\n> GraphQL type system authors must not define any types, fields, arguments,\n> or any other type system artifact with two leading underscores.\n\nReference: https://github.com/facebook/graphql/blob/master/spec/Section%204%20--%20Introspection.md#naming-conventions\n\n",
    "stderr": "{\"errors\":[{\"message\":\"Compilation failed:\\n---------------------------------------\\n## Locations\\nnofile:0\\n\\nField name \\\"__yyo2pb\\\" starts with two leading underscores.\\n\\nType system artifacts must not begin with two leading underscores.\\n\\n> GraphQL type system authors must not define any types, fields, arguments,\\n> or any other type system artifact with two leading underscores.\\n\\nReference: https://github.com/facebook/graphql/blob/master/spec/Section%204%20--%20Introspection.md#naming-conventions\\n\\n\"}]}"
  },
  {
    "id": "f9df39c2-4008-414d-8a04-da83a32f86e0",
    "runId": "7e79c07d-6ca7-4846-894c-ccddf4dfb6c6",
    "implId": "absinthe",
    "testCaseId": "067e429f/2edf4c47/40f37770",
    "status": "error",
    "expected": {
      "data": {
        "pWI9NE8VQ": {
          "cgu": "str"
        },
        "cgu": "str",
        "__typename": "Object_U92jm3n0Y"
      }
    },
    "error": "Compilation failed:\n---------------------------------------\n## Locations\nnofile:0\n\nField name \"__yyo2pb\" starts with two leading underscores.\n\nType system artifacts must not begin with two leading underscores.\n\n> GraphQL type system authors must not define any types, fields, arguments,\n> or any other type system artifact with two leading underscores.\n\nReference: https://github.com/facebook/graphql/blob/master/spec/Section%204%20--%20Introspection.md#naming-conventions\n\n",
    "stderr": "{\"errors\":[{\"message\":\"Compilation failed:\\n---------------------------------------\\n## Locations\\nnofile:0\\n\\nField name \\\"__yyo2pb\\\" starts with two leading underscores.\\n\\nType system artifacts must not begin with two leading underscores.\\n\\n> GraphQL type system authors must not define any types, fields, arguments,\\n> or any other type system artifact with two leading underscores.\\n\\nReference: https://github.com/facebook/graphql/blob/master/spec/Section%204%20--%20Introspection.md#naming-conventions\\n\\n\"}]}"
  },
  {
    "id": "705c63a7-ca7b-4bfe-8384-e986a06cd009",
    "runId": "7e79c07d-6ca7-4846-894c-ccddf4dfb6c6",
    "implId": "absinthe",
    "testCaseId": "067e429f/2edf4c47/f444c2b7",
    "status": "error",
    "expected": {
      "data": {
        "pWI9NE8VQ": {},
        "cgu": "str",
        "__typename": "Object_U92jm3n0Y"
      }
    },
    "error": "Compilation failed:\n---------------------------------------\n## Locations\nnofile:0\n\nField name \"__yyo2pb\" starts with two leading underscores.\n\nType system artifacts must not begin with two leading underscores.\n\n> GraphQL type system authors must not define any types, fields, arguments,\n> or any other type system artifact with two leading underscores.\n\nReference: https://github.com/facebook/graphql/blob/master/spec/Section%204%20--%20Introspection.md#naming-conventions\n\n",
    "stderr": "{\"errors\":[{\"message\":\"Compilation failed:\\n---------------------------------------\\n## Locations\\nnofile:0\\n\\nField name \\\"__yyo2pb\\\" starts with two leading underscores.\\n\\nType system artifacts must not begin with two leading underscores.\\n\\n> GraphQL type system authors must not define any types, fields, arguments,\\n> or any other type system artifact with two leading underscores.\\n\\nReference: https://github.com/facebook/graphql/blob/master/spec/Section%204%20--%20Introspection.md#naming-conventions\\n\\n\"}]}"
  },
  {
    "id": "190221aa-6843-455b-86c6-ca1b6a9bb23d",
    "runId": "7e79c07d-6ca7-4846-894c-ccddf4dfb6c6",
    "implId": "absinthe",
    "testCaseId": "067e429f/32346071/44136fa3",
    "status": "error",
    "expected": {
      "data": {}
    },
    "error": "Compilation failed:\n---------------------------------------\n## Locations\nnofile:0\n\nField name \"__yyo2pb\" starts with two leading underscores.\n\nType system artifacts must not begin with two leading underscores.\n\n> GraphQL type system authors must not define any types, fields, arguments,\n> or any other type system artifact with two leading underscores.\n\nReference: https://github.com/facebook/graphql/blob/master/spec/Section%204%20--%20Introspection.md#naming-conventions\n\n",
    "stderr": "{\"errors\":[{\"message\":\"Compilation failed:\\n---------------------------------------\\n## Locations\\nnofile:0\\n\\nField name \\\"__yyo2pb\\\" starts with two leading underscores.\\n\\nType system artifacts must not begin with two leading underscores.\\n\\n> GraphQL type system authors must not define any types, fields, arguments,\\n> or any other type system artifact with two leading underscores.\\n\\nReference: https://github.com/facebook/graphql/blob/master/spec/Section%204%20--%20Introspection.md#naming-conventions\\n\\n\"}]}"
  },
  {
    "id": "ef2d0b02-ad35-4652-879e-c47d07ddf02e",
    "runId": "7e79c07d-6ca7-4846-894c-ccddf4dfb6c6",
    "implId": "absinthe",
    "testCaseId": "067e429f/53dcaa6b/44136fa3",
    "status": "error",
    "expected": {
      "data": {
        "__typename": "Object_U92jm3n0Y",
        "pWI9NE8VQ": {
          "__typename": "Object_U92jm3n0Y"
        }
      }
    },
    "error": "Compilation failed:\n---------------------------------------\n## Locations\nnofile:0\n\nField name \"__yyo2pb\" starts with two leading underscores.\n\nType system artifacts must not begin with two leading underscores.\n\n> GraphQL type system authors must not define any types, fields, arguments,\n> or any other type system artifact with two leading underscores.\n\nReference: https://github.com/facebook/graphql/blob/master/spec/Section%204%20--%20Introspection.md#naming-conventions\n\n",
    "stderr": "{\"errors\":[{\"message\":\"Compilation failed:\\n---------------------------------------\\n## Locations\\nnofile:0\\n\\nField name \\\"__yyo2pb\\\" starts with two leading underscores.\\n\\nType system artifacts must not begin with two leading underscores.\\n\\n> GraphQL type system authors must not define any types, fields, arguments,\\n> or any other type system artifact with two leading underscores.\\n\\nReference: https://github.com/facebook/graphql/blob/master/spec/Section%204%20--%20Introspection.md#naming-conventions\\n\\n\"}]}"
  },
  {
    "id": "7e838cc0-4360-4e66-8639-c6fc99469243",
    "runId": "7e79c07d-6ca7-4846-894c-ccddf4dfb6c6",
    "implId": "absinthe",
    "testCaseId": "067e429f/5989b27f/211a8742",
    "status": "error",
    "expected": {
      "data": {
        "cgu": "str",
        "YQJ1O9": {
          "E": {
            "XT00gnpI": "Object_U92jm3n0Y"
          },
          "cgu": "str",
          "gVMW": "Object_U92jm3n0Y"
        }
      }
    },
    "error": "Compilation failed:\n---------------------------------------\n## Locations\nnofile:0\n\nField name \"__yyo2pb\" starts with two leading underscores.\n\nType system artifacts must not begin with two leading underscores.\n\n> GraphQL type system authors must not define any types, fields, arguments,\n> or any other type system artifact with two leading underscores.\n\nReference: https://github.com/facebook/graphql/blob/master/spec/Section%204%20--%20Introspection.md#naming-conventions\n\n",
    "stderr": "{\"errors\":[{\"message\":\"Compilation failed:\\n---------------------------------------\\n## Locations\\nnofile:0\\n\\nField name \\\"__yyo2pb\\\" starts with two leading underscores.\\n\\nType system artifacts must not begin with two leading underscores.\\n\\n> GraphQL type system authors must not define any types, fields, arguments,\\n> or any other type system artifact with two leading underscores.\\n\\nReference: https://github.com/facebook/graphql/blob/master/spec/Section%204%20--%20Introspection.md#naming-conventions\\n\\n\"}]}"
  },
  {
    "id": "b25fb2b6-49bc-4515-83f3-e7807c07ca1d",
    "runId": "7e79c07d-6ca7-4846-894c-ccddf4dfb6c6",
    "implId": "absinthe",
    "testCaseId": "067e429f/5989b27f/2eb49031",
    "status": "error",
    "expected": {
      "data": {
        "cgu": "str",
        "YQJ1O9": {
          "E": {
            "XT00gnpI": "Object_U92jm3n0Y"
          },
          "cgu": "str",
          "gVMW": "Object_U92jm3n0Y"
        }
      }
    },
    "error": "Compilation failed:\n---------------------------------------\n## Locations\nnofile:0\n\nField name \"__yyo2pb\" starts with two leading underscores.\n\nType system artifacts must not begin with two leading underscores.\n\n> GraphQL type system authors must not define any types, fields, arguments,\n> or any other type system artifact with two leading underscores.\n\nReference: https://github.com/facebook/graphql/blob/master/spec/Section%204%20--%20Introspection.md#naming-conventions\n\n",
    "stderr": "{\"errors\":[{\"message\":\"Compilation failed:\\n---------------------------------------\\n## Locations\\nnofile:0\\n\\nField name \\\"__yyo2pb\\\" starts with two leading underscores.\\n\\nType system artifacts must not begin with two leading underscores.\\n\\n> GraphQL type system authors must not define any types, fields, arguments,\\n> or any other type system artifact with two leading underscores.\\n\\nReference: https://github.com/facebook/graphql/blob/master/spec/Section%204%20--%20Introspection.md#naming-conventions\\n\\n\"}]}"
  },
  {
    "id": "82f2a1ed-7731-4a06-8c3f-fd92b4be005a",
    "runId": "7e79c07d-6ca7-4846-894c-ccddf4dfb6c6",
    "implId": "absinthe",
    "testCaseId": "067e429f/5989b27f/b0443fa6",
    "status": "error",
    "expected": {
      "data": {
        "cgu": "str",
        "YQJ1O9": {
          "E": {
            "XT00gnpI": "Object_U92jm3n0Y"
          },
          "cgu": "str",
          "gVMW": "Object_U92jm3n0Y"
        }
      }
    },
    "error": "Compilation failed:\n---------------------------------------\n## Locations\nnofile:0\n\nField name \"__yyo2pb\" starts with two leading underscores.\n\nType system artifacts must not begin with two leading underscores.\n\n> GraphQL type system authors must not define any types, fields, arguments,\n> or any other type system artifact with two leading underscores.\n\nReference: https://github.com/facebook/graphql/blob/master/spec/Section%204%20--%20Introspection.md#naming-conventions\n\n",
    "stderr": "{\"errors\":[{\"message\":\"Compilation failed:\\n---------------------------------------\\n## Locations\\nnofile:0\\n\\nField name \\\"__yyo2pb\\\" starts with two leading underscores.\\n\\nType system artifacts must not begin with two leading underscores.\\n\\n> GraphQL type system authors must not define any types, fields, arguments,\\n> or any other type system artifact with two leading underscores.\\n\\nReference: https://github.com/facebook/graphql/blob/master/spec/Section%204%20--%20Introspection.md#naming-conventions\\n\\n\"}]}"
  }
]
