[
  {
    "id": "4a6e66cc-2ce6-4334-8e54-695b38be3d45",
    "runId": "88533598-eb09-4e46-8052-4aaab8cf1958",
    "implId": "gqlgen",
    "testCaseId": "1a83f1c3/d0cee1b5/69eedd1b",
    "status": "fail",
    "expected": {
      "data": {
        "__typename": "Object_GjrbD",
        "zOSZRbzK": "Object_GjrbD",
        "taKQojG": "Object_GjrbD",
        "xe16FkAgSh": {
          "__typename": "Object_p"
        }
      }
    },
    "actual": {
      "data": null,
      "errors": [
        {
          "message": "Variable \"$qQSvVphTF\" is never used.",
          "locations": [
            {
              "line": 1,
              "column": 8
            }
          ],
          "extensions": {
            "code": "GRAPHQL_VALIDATION_FAILED"
          }
        }
      ]
    }
  },
  {
    "id": "9da5c42e-8640-4cf2-8231-0304dbce1e5f",
    "runId": "88533598-eb09-4e46-8052-4aaab8cf1958",
    "implId": "gqlgen",
    "testCaseId": "1a83f1c3/d0cee1b5/7f8046f0",
    "status": "fail",
    "expected": {
      "data": {
        "__typename": "Object_GjrbD",
        "zOSZRbzK": "Object_GjrbD",
        "taKQojG": "Object_GjrbD",
        "xe16FkAgSh": {
          "__typename": "Object_p"
        }
      }
    },
    "actual": {
      "data": null,
      "errors": [
        {
          "message": "Variable \"$qQSvVphTF\" is never used.",
          "locations": [
            {
              "line": 1,
              "column": 8
            }
          ],
          "extensions": {
            "code": "GRAPHQL_VALIDATION_FAILED"
          }
        }
      ]
    }
  },
  {
    "id": "5dcf85f7-7253-4c09-81c1-71fe65fac874",
    "runId": "88533598-eb09-4e46-8052-4aaab8cf1958",
    "implId": "gqlgen",
    "testCaseId": "1a83f1c3/d0cee1b5/cdcee300",
    "status": "fail",
    "expected": {
      "data": {
        "__typename": "Object_GjrbD",
        "zOSZRbzK": "Object_GjrbD",
        "taKQojG": "Object_GjrbD",
        "xe16FkAgSh": {
          "__typename": "Object_p"
        }
      }
    },
    "actual": {
      "data": null,
      "errors": [
        {
          "message": "Variable \"$qQSvVphTF\" is never used.",
          "locations": [
            {
              "line": 1,
              "column": 8
            }
          ],
          "extensions": {
            "code": "GRAPHQL_VALIDATION_FAILED"
          }
        }
      ]
    }
  },
  {
    "id": "f288c439-e9f6-451a-8126-a2253e6e83f9",
    "runId": "88533598-eb09-4e46-8052-4aaab8cf1958",
    "implId": "gqlgen",
    "testCaseId": "23584ab4/36668d38/69e76ef0",
    "status": "fail",
    "expected": {
      "data": {}
    },
    "actual": {
      "data": null,
      "errors": [
        {
          "message": "Variable \"$g0W3Z\" is never used.",
          "locations": [
            {
              "line": 1,
              "column": 8
            }
          ],
          "extensions": {
            "code": "GRAPHQL_VALIDATION_FAILED"
          }
        }
      ]
    }
  },
  {
    "id": "079b7610-dc90-40e0-81a1-ea64203c3451",
    "runId": "88533598-eb09-4e46-8052-4aaab8cf1958",
    "implId": "gqlgen",
    "testCaseId": "23584ab4/36668d38/bb7c3214",
    "status": "fail",
    "expected": {
      "data": {}
    },
    "actual": {
      "data": null,
      "errors": [
        {
          "message": "Variable \"$g0W3Z\" is never used.",
          "locations": [
            {
              "line": 1,
              "column": 8
            }
          ],
          "extensions": {
            "code": "GRAPHQL_VALIDATION_FAILED"
          }
        }
      ]
    }
  },
  {
    "id": "c0ac0668-9184-4e87-8fdd-8d640306867c",
    "runId": "88533598-eb09-4e46-8052-4aaab8cf1958",
    "implId": "gqlgen",
    "testCaseId": "656ced21/1da08990/3a7eeb80",
    "status": "fail",
    "expected": {
      "data": {
        "qd": {
          "uXrXF": 2,
          "gQel": "id"
        },
        "__typename": "Object_pDiTNo",
        "AF8": {
          "__typename": "Interface_mzAQ_STUB",
          "gQel": "id",
          "vVV8YbNuo": {
            "a3XRo1F": "d9K"
          },
          "uXrXF": 2
        },
        "wtVA2w": "Object_pDiTNo"
      }
    },
    "actual": {
      "data": null,
      "errors": [
        {
          "message": "Variable \"$dAPPn6Ht\" is never used in operation \"EN\".",
          "locations": [
            {
              "line": 1,
              "column": 10
            }
          ],
          "extensions": {
            "code": "GRAPHQL_VALIDATION_FAILED"
          }
        }
      ]
    }
  },
  {
    "id": "8d259038-ca41-46e8-8eb2-82cb53602b8f",
    "runId": "88533598-eb09-4e46-8052-4aaab8cf1958",
    "implId": "gqlgen",
    "testCaseId": "656ced21/1da08990/b9fe7f55",
    "status": "fail",
    "expected": {
      "data": {
        "qd": {
          "uXrXF": 2,
          "gQel": "id"
        },
        "__typename": "Object_pDiTNo",
        "AF8": {
          "__typename": "Interface_mzAQ_STUB",
          "gQel": "id",
          "vVV8YbNuo": {
            "a3XRo1F": "d9K"
          },
          "uXrXF": 2
        },
        "wtVA2w": "Object_pDiTNo"
      }
    },
    "actual": {
      "data": null,
      "errors": [
        {
          "message": "Variable \"$dAPPn6Ht\" is never used in operation \"EN\".",
          "locations": [
            {
              "line": 1,
              "column": 10
            }
          ],
          "extensions": {
            "code": "GRAPHQL_VALIDATION_FAILED"
          }
        }
      ]
    }
  },
  {
    "id": "a8f114fd-55ee-422e-8628-1e6b28008be4",
    "runId": "88533598-eb09-4e46-8052-4aaab8cf1958",
    "implId": "gqlgen",
    "testCaseId": "8454a0ec/8b668e1b/244dd359",
    "status": "fail",
    "expected": {
      "data": {
        "__typename": "Object_bosrvz3e8N",
        "tqZn": {
          "iHe0": true
        }
      }
    },
    "actual": {
      "data": null,
      "errors": [
        {
          "message": "Variable \"$bceQfmN\" is never used in operation \"L9_M0t7\".",
          "locations": [
            {
              "line": 1,
              "column": 15
            }
          ],
          "extensions": {
            "code": "GRAPHQL_VALIDATION_FAILED"
          }
        }
      ]
    }
  },
  {
    "id": "f65bfe08-710d-4dae-8626-50f4d77aa30f",
    "runId": "88533598-eb09-4e46-8052-4aaab8cf1958",
    "implId": "gqlgen",
    "testCaseId": "8454a0ec/8b668e1b/5d8b703f",
    "status": "fail",
    "expected": {
      "data": {
        "__typename": "Object_bosrvz3e8N",
        "tqZn": {
          "iHe0": true
        }
      }
    },
    "actual": {
      "data": null,
      "errors": [
        {
          "message": "Variable \"$bceQfmN\" is never used in operation \"L9_M0t7\".",
          "locations": [
            {
              "line": 1,
              "column": 15
            }
          ],
          "extensions": {
            "code": "GRAPHQL_VALIDATION_FAILED"
          }
        }
      ]
    }
  },
  {
    "id": "ebba9a15-f013-4f48-84ba-ba191fa381bd",
    "runId": "88533598-eb09-4e46-8052-4aaab8cf1958",
    "implId": "gqlgen",
    "testCaseId": "8fc8855d/0bfc42c4/f68c37cc",
    "status": "error",
    "expected": {
      "data": {
        "yL7XTu": {
          "q": "J9_v"
        },
        "__typename": "Object_W"
      }
    },
    "error": "socket hang up"
  }
]
