[
  {
    "id": "b2bb5401-02c1-446a-8e29-a11c2ca4e444",
    "runId": "21b0de37-4a57-4f13-9a14-30957843ec8b",
    "implId": "graphql-go",
    "testCaseId": "03573f34/2e32a08b/08277c86",
    "status": "fail",
    "expected": {
      "data": {
        "__typename": "Object_lpJFn",
        "H3Nl_": "Object_lpJFn",
        "puaq39dlg": {
          "deWZL": "XtCw_c"
        }
      }
    },
    "actual": {
      "data": null,
      "errors": [
        {
          "message": "Syntax Error GraphQL request (1:33) Expected $, found @\n\n1: query ($kJ8hrxR: Boolean! = true@Directive_RtXxkf) {\n                                   ^\n2:   ...Fragment_Q\n",
          "locations": [
            {
              "line": 1,
              "column": 33
            }
          ]
        }
      ]
    }
  },
  {
    "id": "79f405bc-92cd-4fee-8a42-93dd085d1640",
    "runId": "21b0de37-4a57-4f13-9a14-30957843ec8b",
    "implId": "graphql-go",
    "testCaseId": "03573f34/2e32a08b/179ab86c",
    "status": "fail",
    "expected": {
      "data": {
        "__typename": "Object_lpJFn",
        "H3Nl_": "Object_lpJFn",
        "puaq39dlg": {
          "deWZL": "XtCw_c"
        }
      }
    },
    "actual": {
      "data": null,
      "errors": [
        {
          "message": "Syntax Error GraphQL request (1:33) Expected $, found @\n\n1: query ($kJ8hrxR: Boolean! = true@Directive_RtXxkf) {\n                                   ^\n2:   ...Fragment_Q\n",
          "locations": [
            {
              "line": 1,
              "column": 33
            }
          ]
        }
      ]
    }
  },
  {
    "id": "4228b653-950b-40d4-84b0-b3cd67a8fb60",
    "runId": "21b0de37-4a57-4f13-9a14-30957843ec8b",
    "implId": "graphql-go",
    "testCaseId": "03573f34/844439df/3cbd2fee",
    "status": "fail",
    "expected": {
      "data": {
        "__typename": "Object_lpJFn"
      }
    },
    "actual": {
      "data": null,
      "errors": [
        {
          "message": "Syntax Error GraphQL request (1:36) Expected $, found @\n\n1: query y90y6ZiH9($u4jGeH6z: Boolean!@Directive_RtXxkf) {\n                                      ^\n2:   ... on Object_lpJFn {\n",
          "locations": [
            {
              "line": 1,
              "column": 36
            }
          ]
        }
      ]
    }
  },
  {
    "id": "d81977a2-0f1d-43ad-8a69-f5a5e7921e3f",
    "runId": "21b0de37-4a57-4f13-9a14-30957843ec8b",
    "implId": "graphql-go",
    "testCaseId": "03573f34/844439df/64d17f61",
    "status": "fail",
    "expected": {
      "data": {
        "__typename": "Object_lpJFn"
      }
    },
    "actual": {
      "data": null,
      "errors": [
        {
          "message": "Syntax Error GraphQL request (1:36) Expected $, found @\n\n1: query y90y6ZiH9($u4jGeH6z: Boolean!@Directive_RtXxkf) {\n                                      ^\n2:   ... on Object_lpJFn {\n",
          "locations": [
            {
              "line": 1,
              "column": 36
            }
          ]
        }
      ]
    }
  },
  {
    "id": "7d7184bb-6c9b-466d-8484-eb511c7f71c6",
    "runId": "21b0de37-4a57-4f13-9a14-30957843ec8b",
    "implId": "graphql-go",
    "testCaseId": "03573f34/db6ebcb1/457e9b63",
    "status": "fail",
    "expected": {
      "data": {
        "P": "Object_lpJFn",
        "oM": "Object_lpJFn"
      }
    },
    "actual": {
      "data": null,
      "errors": [
        {
          "message": "Variable \"$rbEuY2\" of type \"Boolean!\" is required and will not use the default value. Perhaps you meant to use type \"Boolean\".",
          "locations": [
            {
              "line": 1,
              "column": 36
            }
          ]
        }
      ]
    }
  },
  {
    "id": "acf1db6f-84f2-46dd-864e-2c636c876083",
    "runId": "21b0de37-4a57-4f13-9a14-30957843ec8b",
    "implId": "graphql-go",
    "testCaseId": "03573f34/db6ebcb1/b116a709",
    "status": "fail",
    "expected": {
      "data": {
        "P": "Object_lpJFn"
      }
    },
    "actual": {
      "data": null,
      "errors": [
        {
          "message": "Variable \"$rbEuY2\" of type \"Boolean!\" is required and will not use the default value. Perhaps you meant to use type \"Boolean\".",
          "locations": [
            {
              "line": 1,
              "column": 36
            }
          ]
        }
      ]
    }
  },
  {
    "id": "2cd812e9-ae63-4098-884e-f056f37ae966",
    "runId": "21b0de37-4a57-4f13-9a14-30957843ec8b",
    "implId": "graphql-go",
    "testCaseId": "067e429f/2edf4c47/40f37770",
    "status": "fail",
    "expected": {
      "data": {
        "pWI9NE8VQ": {
          "cgu": "str"
        },
        "cgu": "str",
        "__typename": "Object_U92jm3n0Y"
      }
    },
    "actual": {
      "data": null,
      "errors": [
        {
          "message": "Syntax Error GraphQL request (1:26) Expected $, found @\n\n1: query S4Oq($qLz: Boolean!@Directive_jM3v) {\n                            ^\n2:   pWI9NE8VQ @include(if: true) {\n",
          "locations": [
            {
              "line": 1,
              "column": 26
            }
          ]
        }
      ]
    }
  },
  {
    "id": "a58a4101-0011-42bf-850f-e9e49e147e5d",
    "runId": "21b0de37-4a57-4f13-9a14-30957843ec8b",
    "implId": "graphql-go",
    "testCaseId": "067e429f/2edf4c47/f444c2b7",
    "status": "fail",
    "expected": {
      "data": {
        "pWI9NE8VQ": {},
        "cgu": "str",
        "__typename": "Object_U92jm3n0Y"
      }
    },
    "actual": {
      "data": null,
      "errors": [
        {
          "message": "Syntax Error GraphQL request (1:26) Expected $, found @\n\n1: query S4Oq($qLz: Boolean!@Directive_jM3v) {\n                            ^\n2:   pWI9NE8VQ @include(if: true) {\n",
          "locations": [
            {
              "line": 1,
              "column": 26
            }
          ]
        }
      ]
    }
  },
  {
    "id": "a088f5d2-be8d-4130-8dfc-ca704473c84d",
    "runId": "21b0de37-4a57-4f13-9a14-30957843ec8b",
    "implId": "graphql-go",
    "testCaseId": "067e429f/5989b27f/211a8742",
    "status": "fail",
    "expected": {
      "data": {
        "cgu": "str",
        "YQJ1O9": {
          "E": {
            "XT00gnpI": "Object_U92jm3n0Y"
          },
          "cgu": "str",
          "gVMW": "Object_U92jm3n0Y"
        }
      }
    },
    "actual": {
      "data": null,
      "errors": [
        {
          "message": "Syntax Error GraphQL request (1:78) Unexpected Name \"null\"\n\n1: query rM4r1wm($bTCR: Input_DAY = {fLQczEd : 1.0099292073182443E+308, q9SoK : null}) {\n                                                                                ^\n2:   cgu\n",
          "locations": [
            {
              "line": 1,
              "column": 78
            }
          ]
        }
      ]
    }
  },
  {
    "id": "5e91332d-ccf4-49a7-8375-f52da0414e3f",
    "runId": "21b0de37-4a57-4f13-9a14-30957843ec8b",
    "implId": "graphql-go",
    "testCaseId": "067e429f/5989b27f/2eb49031",
    "status": "fail",
    "expected": {
      "data": {
        "cgu": "str",
        "YQJ1O9": {
          "E": {
            "XT00gnpI": "Object_U92jm3n0Y"
          },
          "cgu": "str",
          "gVMW": "Object_U92jm3n0Y"
        }
      }
    },
    "actual": {
      "data": null,
      "errors": [
        {
          "message": "Syntax Error GraphQL request (1:78) Unexpected Name \"null\"\n\n1: query rM4r1wm($bTCR: Input_DAY = {fLQczEd : 1.0099292073182443E+308, q9SoK : null}) {\n                                                                                ^\n2:   cgu\n",
          "locations": [
            {
              "line": 1,
              "column": 78
            }
          ]
        }
      ]
    }
  }
]
