[
  {
    "id": "a1d842c6-6f9c-499f-87e9-73cbf8786ff6",
    "runId": "ec4eca95-673d-4b24-9e4f-b9972495a49f",
    "implId": "juniper",
    "testCaseId": "03573f34/2e32a08b/08277c86",
    "status": "fail",
    "expected": {
      "data": {
        "__typename": "Object_lpJFn",
        "H3Nl_": "Object_lpJFn",
        "puaq39dlg": {
          "deWZL": "XtCw_c"
        }
      }
    },
    "actual": {
      "data": null,
      "errors": [
        {
          "message": "ValidationError([RuleError { locations: [SourcePosition { index: 28, line: 0, col: 28 }], message: \"Argument \\\"kJ8hrxR\\\" has type \\\"Boolean!\\\" and is not nullable, so it can't have a default value\" }])"
        }
      ]
    }
  },
  {
    "id": "ac43c472-eee9-4c34-84ca-415c3a2d6fbd",
    "runId": "ec4eca95-673d-4b24-9e4f-b9972495a49f",
    "implId": "juniper",
    "testCaseId": "03573f34/2e32a08b/179ab86c",
    "status": "fail",
    "expected": {
      "data": {
        "__typename": "Object_lpJFn",
        "H3Nl_": "Object_lpJFn",
        "puaq39dlg": {
          "deWZL": "XtCw_c"
        }
      }
    },
    "actual": {
      "data": null,
      "errors": [
        {
          "message": "ValidationError([RuleError { locations: [SourcePosition { index: 28, line: 0, col: 28 }], message: \"Argument \\\"kJ8hrxR\\\" has type \\\"Boolean!\\\" and is not nullable, so it can't have a default value\" }])"
        }
      ]
    }
  },
  {
    "id": "d6836a23-8733-4fb4-88ba-ff8bf4a3e705",
    "runId": "ec4eca95-673d-4b24-9e4f-b9972495a49f",
    "implId": "juniper",
    "testCaseId": "03573f34/db6ebcb1/457e9b63",
    "status": "fail",
    "expected": {
      "data": {
        "P": "Object_lpJFn",
        "oM": "Object_lpJFn"
      }
    },
    "actual": {
      "data": null,
      "errors": [
        {
          "message": "ValidationError([RuleError { locations: [SourcePosition { index: 35, line: 0, col: 35 }], message: \"Argument \\\"rbEuY2\\\" has type \\\"Boolean!\\\" and is not nullable, so it can't have a default value\" }])"
        }
      ]
    }
  },
  {
    "id": "30eef947-c58c-4d47-8e8c-39d46558d1f1",
    "runId": "ec4eca95-673d-4b24-9e4f-b9972495a49f",
    "implId": "juniper",
    "testCaseId": "03573f34/db6ebcb1/b116a709",
    "status": "fail",
    "expected": {
      "data": {
        "P": "Object_lpJFn"
      }
    },
    "actual": {
      "data": null,
      "errors": [
        {
          "message": "ValidationError([RuleError { locations: [SourcePosition { index: 35, line: 0, col: 35 }], message: \"Argument \\\"rbEuY2\\\" has type \\\"Boolean!\\\" and is not nullable, so it can't have a default value\" }])"
        }
      ]
    }
  },
  {
    "id": "10e10d2f-cb14-401f-8d34-b494692c9162",
    "runId": "ec4eca95-673d-4b24-9e4f-b9972495a49f",
    "implId": "juniper",
    "testCaseId": "0899731f/9a5daa04/7d1ec464",
    "status": "fail",
    "expected": {
      "data": {
        "k": "iS",
        "sn6N8tbgL": "id",
        "__typename": "Object_ARs"
      }
    },
    "actual": {
      "data": null,
      "errors": [
        {
          "message": "ValidationError([RuleError { locations: [SourcePosition { index: 27, line: 0, col: 27 }], message: \"Argument \\\"b\\\" has type \\\"Boolean!\\\" and is not nullable, so it can't have a default value\" }])"
        }
      ]
    }
  },
  {
    "id": "a0a0e360-7449-4bfa-8ab1-12b801ecdca9",
    "runId": "ec4eca95-673d-4b24-9e4f-b9972495a49f",
    "implId": "juniper",
    "testCaseId": "0899731f/9a5daa04/fc0f22db",
    "status": "fail",
    "expected": {
      "data": {
        "k": "iS",
        "sn6N8tbgL": "id",
        "__typename": "Object_ARs"
      }
    },
    "actual": {
      "data": null,
      "errors": [
        {
          "message": "ValidationError([RuleError { locations: [SourcePosition { index: 27, line: 0, col: 27 }], message: \"Argument \\\"b\\\" has type \\\"Boolean!\\\" and is not nullable, so it can't have a default value\" }])"
        }
      ]
    }
  },
  {
    "id": "02d703a2-2394-4a28-8789-e285887d1e3b",
    "runId": "ec4eca95-673d-4b24-9e4f-b9972495a49f",
    "implId": "juniper",
    "testCaseId": "0d5cbb16/46b60c5e/19de0fe7",
    "status": "fail",
    "expected": {
      "data": {}
    },
    "actual": {
      "data": null,
      "errors": [
        {
          "message": "ValidationError([RuleError { locations: [SourcePosition { index: 25, line: 0, col: 25 }], message: \"Argument \\\"r_1T\\\" has type \\\"Boolean!\\\" and is not nullable, so it can't have a default value\" }])"
        }
      ]
    }
  },
  {
    "id": "0348593c-7b6b-4fff-86e5-6ea93f0be8eb",
    "runId": "ec4eca95-673d-4b24-9e4f-b9972495a49f",
    "implId": "juniper",
    "testCaseId": "0d5cbb16/46b60c5e/c9e8ed04",
    "status": "fail",
    "expected": {
      "data": {}
    },
    "actual": {
      "data": null,
      "errors": [
        {
          "message": "ValidationError([RuleError { locations: [SourcePosition { index: 25, line: 0, col: 25 }], message: \"Argument \\\"r_1T\\\" has type \\\"Boolean!\\\" and is not nullable, so it can't have a default value\" }])"
        }
      ]
    }
  },
  {
    "id": "1c080358-0f7c-4554-8af0-8b8fd7fca733",
    "runId": "ec4eca95-673d-4b24-9e4f-b9972495a49f",
    "implId": "juniper",
    "testCaseId": "15e18fa2/d15b7a55/fc962535",
    "status": "fail",
    "expected": {
      "data": {
        "__typename": "Object_ivbme4MRt"
      }
    },
    "actual": {
      "data": null,
      "errors": [
        {
          "message": "ValidationError([RuleError { locations: [SourcePosition { index: 14, line: 0, col: 14 }], message: \"Variable \\\"$vjo3\\\" is not used by operation \\\"eCk0o4m\\\"\" }])"
        }
      ]
    }
  },
  {
    "id": "45af5f12-f2a8-4729-8828-46009172618d",
    "runId": "ec4eca95-673d-4b24-9e4f-b9972495a49f",
    "implId": "juniper",
    "testCaseId": "1790a98f/f9b9f6bf/02bb3985",
    "status": "fail",
    "expected": {
      "data": {
        "__typename": "Object_SE",
        "h2hpA": [
          {
            "__typename": "Object_qIcsq7M",
            "RXy": [
              {
                "u5AJ72UL": "RIq727Xz"
              },
              {
                "u5AJ72UL": "RIq727Xz"
              }
            ]
          },
          {
            "__typename": "Object_qIcsq7M",
            "RXy": [
              {
                "u5AJ72UL": "RIq727Xz"
              },
              {
                "u5AJ72UL": "RIq727Xz"
              }
            ]
          }
        ]
      }
    },
    "actual": {
      "data": null,
      "errors": [
        {
          "message": "ValidationError([RuleError { locations: [SourcePosition { index: 28, line: 0, col: 28 }], message: \"Argument \\\"tA\\\" has type \\\"Boolean!\\\" and is not nullable, so it can't have a default value\" }])"
        }
      ]
    }
  }
]
